Workbook

Sheet Claude Log
A1: Turn # | B1: Date | C1: User Request | D1: Action Taken | E1: Details | F1: Outcome
A2: 1 | B2: 46149 | C2: Review the spreadsheet and ensure all formulas are correct and working. | D2: Audited all 5 sheets; fixed 3 broken formulas in Assumptions; flagged structural issues (mostly hardcoded values, label conflicts) for user decision. | E2: Fixes: Assumptions!B8 =B5*B6 (#VALUE!) → =B6*B7 = $12,340,290 (units × cost/unit). Assumptions!B15 =B13 (returned $1.4M, wrong reference for Year 20 equity return) → hardcoded 600000 to match Dashboard B11. Assumptions!B23 =1-B19 (returned 98%, computed off rent growth) → =1-B22 = 40% (correct NFP share). Verified math throughout: PMT $300,448 ✓ at 4.3%/50yr/$6.17M; Y1 NOI $477,945 ✓; DSCR 1.59x ✓; 60/40 NCF splits ✓; 24-Unit alt all ties ✓. | F2: Formula bugs resolved. Outstanding issues raised to user: (a) Pro Forma, Dashboard, Landowner Waterfall, 24-Unit Alternative are 100% hardcoded — not driven by Assumptions; (b) 'Landowner Retained Equity' label means $1M in Assumptions!B14 but $600K on Dashboard B10; (c) Landowner Waterfall column C labeled 'cumulative' but values are incremental — column D holds true cumulatives.
A3: 2 | B3: 46149 | C3: Make the model better — implement Tier 1 improvements (wire everything to formulas). | D3: Converted the entire workbook from hardcoded snapshot to a live formula-driven model. Assumptions sheet is now the single source of inputs; Pro Forma, Dashboard, Landowner Waterfall, and 24-Unit Alternative all derive from it. | E3: Assumptions: added DERIVED block (E5:E9) with mortgage principal =B8*B27, annual DS =-PMT(B32/12,B33*12,E5)*12, GPR Y1, capital stack check; renamed B14 'Value Below Asking'; color-coded blue inputs / black formulas; applied $/% number formats. Pro Forma: rebuilt all 16 rows × 21 cols as draggable formulas; B-col pulls from Assumptions, C-U applies rent growth (1+B19), debt service constant from $E$6, distributions from $B$22/$B$23 share assumptions, mortgage amort uses CUMPRINC for paydown and balance, V-col is SUM totals. Dashboard: all 15 KPIs (B5:B19) and capital stack (B22:C26) wired to formulas. Landowner Waterfall: relabeled column C 'Period Income' (incremental), column D 'Cumulative'; renamed rows 6-9 to 'Years 2-5/6-10/11-15/16-20'; all C-col cells now =SUM over Pro Forma year ranges; D-col running cumulative; comparison block B18:B22 wired. 24-Unit Alternative: only B5 (units=24) and B8 (rent=2200) remain inputs; everything else derives from shared Assumptions; B15 uses growing-annuity closed form for 20-yr cum income. Verified end-to-end: changed rent 2150→2300, Dashboard NOI rose 477,945→511,290 and DSCR 1.59→1.70; reverted cleanly. | F3: Model is fully live. Original numbers preserved exactly: TPC $12,340,290; Y1 NOI $477,945; DSCR 1.59x; 20-yr landowner cum income $3,362,302; total landowner return $5,362,302; 24-unit alt total $4,819,473. Tier 2 (sensitivity tables, scenario toggle, IRR, charts, break-even) and Tier 3 polish remain available on request.
A4: 3 | B4: 46149 | C4: Anything else we can do to improve the model? | D4: Presented Tier 2 / Tier 3 / Tier 4 enhancement menu and recommended a combination. | E4: Tier 2: IRR & equity multiple for landowner; sensitivity table (rent × vacancy); Base/Downside/Upside scenario toggle; break-even rent solver; opex line-item detail. Tier 3: charts (capital stack donut, NCF stacked column, cumulative return line, DSCR-by-year); Sources & Uses table; stabilized cap rate / refinance test; print layout; data validation on inputs. Tier 4: separate rent vs opex inflation; vacancy lease-up curve; MLI Select scoring proxy. | F4: Awaiting user selection. Recommended bundle: items 1+2+3+6 (IRR + sensitivity + scenarios + charts) for BCH/lender pitch readiness.
A5: 4 | B5: 46149 | C5: Implement all 4 enhancement bundles — IRR/EM, sensitivity, scenario toggle, charts. | D5: Added time-weighted return metrics, two sensitivity tables, three-state scenario toggle with dropdown, and four charts to the Dashboard. New 'Sensitivity' sheet created. | E5: (1) IRR & EM on Landowner Waterfall: built 21-period cash flow series in B30:V30 (t=0 = land contributed -$2M + $1.4M Day 1 cash; t=1..19 = annual NCF distributions; t=20 = NCF + $600K equity return). =IRR(B30:V30) yields 22.04%; equity multiple = (Day1+CumIncome+Y20Equity)/Land = 2.68x. Surfaced both on Dashboard B20/B21 (inserted 2 rows; capital-stack rows auto-shifted). (2) Sensitivity sheet: 7×7 DSCR table (rent $2,000-$2,300 × vacancy 2-8%) with conditional formatting (red <1.10, green >=1.30) and yellow base case at E8; second 7×7 table for 20-yr Landowner Cum Income (rent × rent growth 1-4%) using closed-form growing annuity. (3) Scenario toggle on Assumptions D11:G18: dropdown at E12 (Downside/Base/Upside) drives B18/B19/B20/B21 via INDEX/MATCH. Tested cascade — Downside DSCR 1.34x/IRR 13.8%, Base 1.59x/22.0%, Upside 1.82x/30.3%. (4) Charts on Dashboard: Capital Stack donut (E1:K12), Cumulative Landowner Income line (L1:R12), Annual NCF Distributions stacked column (E13:K27), DSCR by Year + 1.10 threshold line (L13:R27). Chart data blocks added to Pro Forma rows 18-30. | F5: Model is now decision-ready: live IRR/EM, scenario stress testing, two-way sensitivity, and visual charts. Zero formula errors across 6 sheets. Base case verified: TPC $12.34M / NOI $478K / DSCR 1.59x / IRR 22.0% / EM 2.68x. Tier 2 items remaining (break-even rent solver, opex line-item detail) and Tier 3-4 items (S&U table, cap-rate test, print layout, data validation, opex inflation, lease-up curve, MLI scoring) available on request.

Sheet Dashboard
A1: 2008 BRIMLEY ROAD — Common Ground Initiative Model
A2: 30-Unit Purpose-Built Rental · Toronto (Scarborough), ON · BCH/CMHC Financial Model
A4: KEY METRICS
A5: Total Project Cost | B5: =Assumptions!B8 -> 12340290
A6: Land Valuation (BCH pitch) | B6: =Assumptions!B12 -> 2000000
A7: Total Units | B7: =Assumptions!B6 -> 30
A8: Cost per Unit | B8: =Assumptions!B7 -> 411343
A9: Day 1 Cash to Landowner | B9: =Assumptions!B13 -> 1400000
A10: Landowner Retained Equity | B10: =Assumptions!B8*Assumptions!B29 -> 599738.09
A11: Year 20 Equity Return | B11: =Assumptions!B15 -> 600000
A12: Year 1 NOI | B12: ='Pro Forma'!B8 -> 477945
A13: Year 1 Annual Debt Service | B13: ='Pro Forma'!B9 -> 300448.47
A14: Year 1 Net Cash Flow | B14: ='Pro Forma'!B10 -> 177496.53
A15: DSCR (Year 1) | B15: ='Pro Forma'!B8/'Pro Forma'!B9 -> 1.5907719
A16: LTV | B16: =Assumptions!B27 -> 0.5
A17: Break-even Occupancy | B17: =('Pro Forma'!B7+'Pro Forma'!B9)/'Pro Forma'!B4 -> 0.72067632
A18: Landowner 20-Yr Cumulative Income | B18: ='Pro Forma'!V12 -> 3362302.2
A19: Total 20-Yr Return to Landowner | B19: =B9+B18+B11 -> 5362302.2
A20: Landowner IRR | B20: ='Landowner Waterfall'!B28 -> 0.22035623 | E20: BCH Federal Grant | F20: =C24 -> 4936116
A21: Landowner Equity Multiple | B21: ='Landowner Waterfall'!B29 -> 2.6811511 | E21: CMHC MLI Mortgage | F21: =C25 -> 6170145
A22: CAPITAL STACK
A23: Source | B23: % | C23: Amount | D23: Treatment
A24: BCH Federal Grant | B24: =Assumptions!B26 -> 0.4 | C24: =B24*$B$5 -> 4936116 | D24: Forgivable, vests over 20 years
A25: CMHC MLI Mortgage | B25: =Assumptions!B27 -> 0.5 | C25: =B25*$B$5 -> 6170145 | D25: 50-yr amortization, ~4.3% rate
A26: Municipal Incentives | B26: =Assumptions!B28 -> 0.0514 | C26: =B26*$B$5 -> 634290.91 | D26: DC waivers, property tax relief
A27: Landowner Equity | B27: =Assumptions!B29 -> 0.0486 | C27: =B27*$B$5 -> 599738.09 | D27: Land contribution at appraised value
A28: TOTAL | B28: =SUM(B24:B27) -> 1 | C28: =SUM(C24:C27) -> 12340290

Sheet Assumptions
A1: Project Assumptions — Editable Inputs
A2: Blue = inputs that can be changed for sensitivity analysis
A4: PROJECT
A5: Project Name | B5: 2008 Brimley Road | D5: Mortgage Principal ($) | E5: =B8*B27 -> 6170145
A6: Total Units | B6: 30 | D6: Annual Debt Service ($) | E6: =-PMT(B32/12,B33*12,E5)*12 -> 300448.47
A7: Cost per Unit ($) | B7: 411343 | D7: Monthly PMT ($) | E7: =-PMT(B32/12,B33*12,E5) -> 25037.373
A8: Total Development Cost ($) | B8: =B6*B7 -> 12340290 | D8: Annual GPR Year 1 ($) | E8: =B6*B18*12 -> 774000
D9: Capital Stack Check | E9: =B26+B27+B28+B29 -> 1
A10: LAND
A11: Owner Asking Price ($) | B11: 3000000 | D11: SCENARIO TOGGLE
A12: BCH Pitch Valuation ($) | B12: 2000000 | D12: Active Scenario → | E12: Base
A13: Day 1 Cash to Landowner ($) | B13: 1400000
A14: Value Below Asking ($) | B14: =B11-B12 -> 1000000 | D14: Driver | E14: Downside | F14: Base | G14: Upside
A15: Year 20 Equity Return ($) | B15: 600000 | D15: Avg Monthly Rent ($) | E15: 2000 | F15: 2150 | G15: 2300
D16: Rent Growth (%) | E16: 0.015 | F16: 0.02 | G16: 0.03
A17: OPERATING | E17: 0.07 | F17: 0.05 | G17: 0.03
A18: Average Monthly Rent ($) | B18: =INDEX($E$15:$G$15,MATCH($E$12,$E$14:$G$14,0)) -> 2150 | D18: OpEx Ratio (% of EGI) | E18: 0.4 | F18: 0.35 | G18: 0.32
A19: Annual Rent Growth (%) | B19: =INDEX($E$16:$G$16,MATCH($E$12,$E$14:$G$14,0)) -> 0.02
A20: Vacancy Rate (%) | B20: =INDEX($E$17:$G$17,MATCH($E$12,$E$14:$G$14,0)) -> 0.05
A21: Operating Expense Ratio (% of EGI) | B21: =INDEX($E$18:$G$18,MATCH($E$12,$E$14:$G$14,0)) -> 0.35
A22: Landowner NCF Share (%) | B22: 0.6
A23: NFP NCF Share (%) | B23: =1-B22 -> 0.4
A25: CAPITAL STACK
A26: BCH Grant (%) | B26: 0.4
A27: CMHC MLI Mortgage (%) | B27: 0.5
A28: Municipal Incentives (%) | B28: 0.0514
A29: Landowner Equity (%) | B29: 0.0486
A31: MORTGAGE
A32: CMHC MLI Rate (%) | B32: 0.043
A33: Amortization (years) | B33: 50
A34: CMHC Minimum DSCR | B34: 1.1
A35: Term (years) | B35: 20

Sheet Pro Forma
A1: 20-Year Operating Pro Forma
A3: Line Item | B3: Year 1 | C3: Year 2 | D3: Year 3 | E3: Year 4 | F3: Year 5 | G3: Year 6 | H3: Year 7 | I3: Year 8 | J3: Year 9 | K3: Year 10 | L3: Year 11 | M3: Year 12 | N3: Year 13 | O3: Year 14 | P3: Year 15 | Q3: Year 16 | R3: Year 17 | S3: Year 18 | T3: Year 19 | U3: Year 20 | V3: 20-Yr Cum
A4: Gross Potential Rent | B4: =Assumptions!E8 -> 774000 | C4: =B4*(1+Assumptions!$B$19) -> 789480 | D4: =C4*(1+Assumptions!$B$19) -> 805269.6 | E4: =D4*(1+Assumptions!$B$19) -> 821374.99 | F4: =E4*(1+Assumptions!$B$19) -> 837802.49 | G4: =F4*(1+Assumptions!$B$19) -> 854558.54 | H4: =G4*(1+Assumptions!$B$19) -> 871649.71 | I4: =H4*(1+Assumptions!$B$19) -> 889082.71 | J4: =I4*(1+Assumptions!$B$19) -> 906864.36 | ... U4: =T4*(1+Assumptions!$B$19) -> 1127571.8 | V4: =SUM(B4:U4) -> 18806164
A5: Less: Vacancy Loss | B5: =B4*Assumptions!$B$20 -> 38700 | C5: =C4*Assumptions!$B$20 -> 39474 | D5: =D4*Assumptions!$B$20 -> 40263.48 | E5: =E4*Assumptions!$B$20 -> 41068.75 | F5: =F4*Assumptions!$B$20 -> 41890.125 | G5: =G4*Assumptions!$B$20 -> 42727.927 | H5: =H4*Assumptions!$B$20 -> 43582.486 | I5: =I4*Assumptions!$B$20 -> 44454.135 | ... U5: =U4*Assumptions!$B$20 -> 56378.592 | V5: =SUM(B5:U5) -> 940308.21
A6: Effective Gross Income | B6: =B4-B5 -> 735300 | C6: =C4-C5 -> 750006 | D6: =D4-D5 -> 765006.12 | E6: =E4-E5 -> 780306.24 | F6: =F4-F5 -> 795912.37 | G6: =G4-G5 -> 811830.61 | H6: =H4-H5 -> 828067.23 | I6: =I4-I5 -> 844628.57 | ... U6: =U4-U5 -> 1071193.3 | V6: =SUM(B6:U6) -> 17865856
A7: Less: Operating Expenses | B7: =B6*Assumptions!$B$21 -> 257355 | C7: =C6*Assumptions!$B$21 -> 262502.1 | D7: =D6*Assumptions!$B$21 -> 267752.14 | E7: =E6*Assumptions!$B$21 -> 273107.18 | F7: =F6*Assumptions!$B$21 -> 278569.33 | G7: =G6*Assumptions!$B$21 -> 284140.72 | H7: =H6*Assumptions!$B$21 -> 289823.53 | I7: =I6*Assumptions!$B$21 -> 295620 | ... U7: =U6*Assumptions!$B$21 -> 374917.64 | V7: =SUM(B7:U7) -> 6253049.6
A8: Net Operating Income (NOI) | B8: =B6-B7 -> 477945 | C8: =C6-C7 -> 487503.9 | D8: =D6-D7 -> 497253.98 | E8: =E6-E7 -> 507199.06 | F8: =F6-F7 -> 517343.04 | G8: =G6-G7 -> 527689.9 | H8: =H6-H7 -> 538243.7 | I8: =I6-I7 -> 549008.57 | ... U8: =U6-U7 -> 696275.62 | V8: =SUM(B8:U8) -> 11612806
A9: Less: Annual Debt Service | B9: =Assumptions!$E$6 -> 300448.47 | C9: =Assumptions!$E$6 -> 300448.47 | D9: =Assumptions!$E$6 -> 300448.47 | E9: =Assumptions!$E$6 -> 300448.47 | F9: =Assumptions!$E$6 -> 300448.47 | G9: =Assumptions!$E$6 -> 300448.47 | H9: =Assumptions!$E$6 -> 300448.47 | I9: =Assumptions!$E$6 -> 300448.47 | ... U9: =Assumptions!$E$6 -> 300448.47 | V9: =SUM(B9:U9) -> 6008969.5
A10: Net Cash Flow (NCF) | B10: =B8-B9 -> 177496.53 | C10: =C8-C9 -> 187055.43 | D10: =D8-D9 -> 196805.5 | E10: =E8-E9 -> 206750.58 | F10: =F8-F9 -> 216894.57 | G10: =G8-G9 -> 227241.43 | H10: =H8-H9 -> 237795.22 | I10: =I8-I9 -> 248560.1 | ... U10: =U8-U9 -> 395827.14 | V10: =SUM(B10:U10) -> 5603836.9
A12: Landowner Distribution (60%) | B12: =B10*Assumptions!$B$22 -> 106497.92 | C12: =C10*Assumptions!$B$22 -> 112233.26 | D12: =D10*Assumptions!$B$22 -> 118083.3 | E12: =E10*Assumptions!$B$22 -> 124050.35 | F12: =F10*Assumptions!$B$22 -> 130136.74 | G12: =G10*Assumptions!$B$22 -> 136344.86 | H12: =H10*Assumptions!$B$22 -> 142677.13 | I12: =I10*Assumptions!$B$22 -> 149136.06 | ... U12: =U10*Assumptions!$B$22 -> 237496.29 | V12: =SUM(B12:U12) -> 3362302.2
A13: NFP Distribution (40%) | B13: =B10*Assumptions!$B$23 -> 70998.611 | C13: =C10*Assumptions!$B$23 -> 74822.171 | D13: =D10*Assumptions!$B$23 -> 78722.202 | E13: =E10*Assumptions!$B$23 -> 82700.234 | F13: =F10*Assumptions!$B$23 -> 86757.826 | G13: =G10*Assumptions!$B$23 -> 90896.571 | H13: =H10*Assumptions!$B$23 -> 95118.09 | I13: =I10*Assumptions!$B$23 -> 99424.039 | ... U13: =U10*Assumptions!$B$23 -> 158330.86 | V13: =SUM(B13:U13) -> 2241534.8
A15: Cumulative Mortgage Paydown | B15: =-CUMPRINC(Assumptions!$B$32/12,Assumptions!$B$33*12,Assumptions!$E$5,1,12,0) -> 35832.973 | C15: =B15+(-CUMPRINC(Assumptions!$B$32/12,Assumptions!$B$33*12,Assumptions!$E$5,(COLUMN()-2)*12+1,(COLUMN()-1)*12,0)) -> 73237.497 | D15: =C15+(-CUMPRINC(Assumptions!$B$32/12,Assumptions!$B$33*12,Assumptions!$E$5,(COLUMN()-2)*12+1,(COLUMN()-1)*12,0)) -> 112282.5 | E15: =D15+(-CUMPRINC(Assumptions!$B$32/12,Assumptions!$B$33*12,Assumptions!$E$5,(COLUMN()-2)*12+1,(COLUMN()-1)*12,0)) -> 153039.92 | F15: =E15+(-CUMPRINC(Assumptions!$B$32/12,Assumptions!$B$33*12,Assumptions!$E$5,(COLUMN()-2)*12+1,(COLUMN()-1)*12,0)) -> 195584.86 | G15: =F15+(-CUMPRINC(Assumptions!$B$32/12,Assumptions!$B$33*12,Assumptions!$E$5,(COLUMN()-2)*12+1,(COLUMN()-1)*12,0)) -> 239995.73 | H15: =G15+(-CUMPRINC(Assumptions!$B$32/12,Assumptions!$B$33*12,Assumptions!$E$5,(COLUMN()-2)*12+1,(COLUMN()-1)*12,0)) -> 286354.36 | I15: =H15+(-CUMPRINC(Assumptions!$B$32/12,Assumptions!$B$33*12,Assumptions!$E$5,(COLUMN()-2)*12+1,(COLUMN()-1)*12,0)) -> 334746.16 | J15: =I15+(-CUMPRINC(Assumptions!$B$32/12,Assumptions!$B$33*12,Assumptions!$E$5,(COLUMN()-2)*12+1,(COLUMN()-1)*12,0)) -> 385260.32 | ... U15: =T15+(-CUMPRINC(Assumptions!$B$32/12,Assumptions!$B$33*12,Assumptions!$E$5,(COLUMN()-2)*12+1,(COLUMN()-1)*12,0)) -> 1110775.9 | V15: =U15 -> 1110775.9
A16: Mortgage Balance EOY | B16: =Assumptions!$E$5-B15 -> 6134312 | C16: =Assumptions!$E$5-C15 -> 6096907.5 | D16: =Assumptions!$E$5-D15 -> 6057862.5 | E16: =Assumptions!$E$5-E15 -> 6017105.1 | F16: =Assumptions!$E$5-F15 -> 5974560.1 | G16: =Assumptions!$E$5-G15 -> 5930149.3 | H16: =Assumptions!$E$5-H15 -> 5883790.6 | I16: =Assumptions!$E$5-I15 -> 5835398.8 | ... U16: =Assumptions!$E$5-U15 -> 5059369.1
A18: Year (chart label) | B18: 1 | C18: =B18+1 -> 2 | D18: =C18+1 -> 3 | E18: =D18+1 -> 4 | F18: =E18+1 -> 5 | G18: =F18+1 -> 6 | H18: =G18+1 -> 7 | I18: =H18+1 -> 8 | J18: =I18+1 -> 9 | ... U18: =T18+1 -> 20
A19: Landowner Distribution | B19: =B12 -> 106497.92 | C19: =C12 -> 112233.26 | D19: =D12 -> 118083.3 | E19: =E12 -> 124050.35 | F19: =F12 -> 130136.74 | G19: =G12 -> 136344.86 | H19: =H12 -> 142677.13 | I19: =I12 -> 149136.06 | ... U19: =U12 -> 237496.29
A20: NFP Distribution | B20: =B13 -> 70998.611 | C20: =C13 -> 74822.171 | D20: =D13 -> 78722.202 | E20: =E13 -> 82700.234 | F20: =F13 -> 86757.826 | G20: =G13 -> 90896.571 | H20: =H13 -> 95118.09 | I20: =I13 -> 99424.039 | ... U20: =U13 -> 158330.86
A21: Cumulative Landowner Income | B21: =B12 -> 106497.92 | C21: =B21+C12 -> 218731.17 | D21: =C21+D12 -> 336814.48 | E21: =D21+E12 -> 460864.83 | F21: =E21+F12 -> 591001.57 | G21: =F21+G12 -> 727346.42 | H21: =G21+H12 -> 870023.56 | I21: =H21+I12 -> 1019159.6 | J21: =I21+J12 -> 1174883.8 | ... U21: =T21+U12 -> 3362302.2
A22: DSCR by Year | B22: =B8/B9 -> 1.5907719 | C22: =C8/C9 -> 1.6225874 | D22: =D8/D9 -> 1.6550391 | E22: =E8/E9 -> 1.6881399 | F22: =F8/F9 -> 1.7219027 | G22: =G8/G9 -> 1.7563408 | H22: =H8/H9 -> 1.7914676 | I22: =I8/I9 -> 1.8272969 | ... U22: =U8/U9 -> 2.3174543
A23: DSCR Min Threshold (1.10) | B23: =Assumptions!$B$34 -> 1.1 | C23: =Assumptions!$B$34 -> 1.1 | D23: =Assumptions!$B$34 -> 1.1 | E23: =Assumptions!$B$34 -> 1.1 | F23: =Assumptions!$B$34 -> 1.1 | G23: =Assumptions!$B$34 -> 1.1 | H23: =Assumptions!$B$34 -> 1.1 | I23: =Assumptions!$B$34 -> 1.1 | ... U23: =Assumptions!$B$34 -> 1.1
A25: Year (chart) | B25: =B18 -> 1 | C25: =C18 -> 2 | D25: =D18 -> 3 | E25: =E18 -> 4 | F25: =F18 -> 5 | G25: =G18 -> 6 | H25: =H18 -> 7 | I25: =I18 -> 8 | ... U25: =U18 -> 20
A26: Cumulative Landowner Income | B26: =B21 -> 106497.92 | C26: =C21 -> 218731.17 | D26: =D21 -> 336814.48 | E26: =E21 -> 460864.83 | F26: =F21 -> 591001.57 | G26: =G21 -> 727346.42 | H26: =H21 -> 870023.56 | I26: =I21 -> 1019159.6 | ... U26: =U21 -> 3362302.2
A28: Year (chart) | B28: =B18 -> 1 | C28: =C18 -> 2 | D28: =D18 -> 3 | E28: =E18 -> 4 | F28: =F18 -> 5 | G28: =G18 -> 6 | H28: =H18 -> 7 | I28: =I18 -> 8 | ... U28: =U18 -> 20
A29: DSCR by Year | B29: =B22 -> 1.5907719 | C29: =C22 -> 1.6225874 | D29: =D22 -> 1.6550391 | E29: =E22 -> 1.6881399 | F29: =F22 -> 1.7219027 | G29: =G22 -> 1.7563408 | H29: =H22 -> 1.7914676 | I29: =I22 -> 1.8272969 | ... U29: =U22 -> 2.3174543
A30: 1.10x Threshold | B30: =B23 -> 1.1 | C30: =C23 -> 1.1 | D30: =D23 -> 1.1 | E30: =E23 -> 1.1 | F30: =F23 -> 1.1 | G30: =G23 -> 1.1 | H30: =H23 -> 1.1 | I30: =I23 -> 1.1 | ... U30: =U23 -> 1.1

Sheet Sensitivity
A1: Sensitivity Analysis
A2: Year 1 DSCR — Rent (rows) × Vacancy (cols). Base case highlighted.
A4: DSCR (Y1) | B4: 0.02 | C4: 0.03 | D4: 0.04 | E4: 0.05 | F4: 0.06 | G4: 0.07 | H4: 0.08
A5: 2000 | B5: =(Assumptions!$B$6*$A5*12*(1-B$4)*(1-Assumptions!$B$21))/Assumptions!$E$6 -> 1.526518 | C5: =(Assumptions!$B$6*$A5*12*(1-C$4)*(1-Assumptions!$B$21))/Assumptions!$E$6 -> 1.5109413 | D5: =(Assumptions!$B$6*$A5*12*(1-D$4)*(1-Assumptions!$B$21))/Assumptions!$E$6 -> 1.4953646 | E5: =(Assumptions!$B$6*$A5*12*(1-E$4)*(1-Assumptions!$B$21))/Assumptions!$E$6 -> 1.4797878 | F5: =(Assumptions!$B$6*$A5*12*(1-F$4)*(1-Assumptions!$B$21))/Assumptions!$E$6 -> 1.4642111 | G5: =(Assumptions!$B$6*$A5*12*(1-G$4)*(1-Assumptions!$B$21))/Assumptions!$E$6 -> 1.4486344 | H5: =(Assumptions!$B$6*$A5*12*(1-H$4)*(1-Assumptions!$B$21))/Assumptions!$E$6 -> 1.4330577
A6: 2050 | B6: =(Assumptions!$B$6*$A6*12*(1-B$4)*(1-Assumptions!$B$21))/Assumptions!$E$6 -> 1.5646809 | C6: =(Assumptions!$B$6*$A6*12*(1-C$4)*(1-Assumptions!$B$21))/Assumptions!$E$6 -> 1.5487148 | D6: =(Assumptions!$B$6*$A6*12*(1-D$4)*(1-Assumptions!$B$21))/Assumptions!$E$6 -> 1.5327487 | E6: =(Assumptions!$B$6*$A6*12*(1-E$4)*(1-Assumptions!$B$21))/Assumptions!$E$6 -> 1.5167825 | F6: =(Assumptions!$B$6*$A6*12*(1-F$4)*(1-Assumptions!$B$21))/Assumptions!$E$6 -> 1.5008164 | G6: =(Assumptions!$B$6*$A6*12*(1-G$4)*(1-Assumptions!$B$21))/Assumptions!$E$6 -> 1.4848503 | H6: =(Assumptions!$B$6*$A6*12*(1-H$4)*(1-Assumptions!$B$21))/Assumptions!$E$6 -> 1.4688841
A7: 2100 | B7: =(Assumptions!$B$6*$A7*12*(1-B$4)*(1-Assumptions!$B$21))/Assumptions!$E$6 -> 1.6028439 | C7: =(Assumptions!$B$6*$A7*12*(1-C$4)*(1-Assumptions!$B$21))/Assumptions!$E$6 -> 1.5864883 | D7: =(Assumptions!$B$6*$A7*12*(1-D$4)*(1-Assumptions!$B$21))/Assumptions!$E$6 -> 1.5701328 | E7: =(Assumptions!$B$6*$A7*12*(1-E$4)*(1-Assumptions!$B$21))/Assumptions!$E$6 -> 1.5537772 | F7: =(Assumptions!$B$6*$A7*12*(1-F$4)*(1-Assumptions!$B$21))/Assumptions!$E$6 -> 1.5374217 | G7: =(Assumptions!$B$6*$A7*12*(1-G$4)*(1-Assumptions!$B$21))/Assumptions!$E$6 -> 1.5210661 | H7: =(Assumptions!$B$6*$A7*12*(1-H$4)*(1-Assumptions!$B$21))/Assumptions!$E$6 -> 1.5047106
A8: 2150 | B8: =(Assumptions!$B$6*$A8*12*(1-B$4)*(1-Assumptions!$B$21))/Assumptions!$E$6 -> 1.6410068 | C8: =(Assumptions!$B$6*$A8*12*(1-C$4)*(1-Assumptions!$B$21))/Assumptions!$E$6 -> 1.6242619 | D8: =(Assumptions!$B$6*$A8*12*(1-D$4)*(1-Assumptions!$B$21))/Assumptions!$E$6 -> 1.6075169 | E8: =(Assumptions!$B$6*$A8*12*(1-E$4)*(1-Assumptions!$B$21))/Assumptions!$E$6 -> 1.5907719 | F8: =(Assumptions!$B$6*$A8*12*(1-F$4)*(1-Assumptions!$B$21))/Assumptions!$E$6 -> 1.574027 | G8: =(Assumptions!$B$6*$A8*12*(1-G$4)*(1-Assumptions!$B$21))/Assumptions!$E$6 -> 1.557282 | H8: =(Assumptions!$B$6*$A8*12*(1-H$4)*(1-Assumptions!$B$21))/Assumptions!$E$6 -> 1.540537
A9: 2200 | B9: =(Assumptions!$B$6*$A9*12*(1-B$4)*(1-Assumptions!$B$21))/Assumptions!$E$6 -> 1.6791698 | C9: =(Assumptions!$B$6*$A9*12*(1-C$4)*(1-Assumptions!$B$21))/Assumptions!$E$6 -> 1.6620354 | D9: =(Assumptions!$B$6*$A9*12*(1-D$4)*(1-Assumptions!$B$21))/Assumptions!$E$6 -> 1.644901 | E9: =(Assumptions!$B$6*$A9*12*(1-E$4)*(1-Assumptions!$B$21))/Assumptions!$E$6 -> 1.6277666 | F9: =(Assumptions!$B$6*$A9*12*(1-F$4)*(1-Assumptions!$B$21))/Assumptions!$E$6 -> 1.6106322 | G9: =(Assumptions!$B$6*$A9*12*(1-G$4)*(1-Assumptions!$B$21))/Assumptions!$E$6 -> 1.5934979 | H9: =(Assumptions!$B$6*$A9*12*(1-H$4)*(1-Assumptions!$B$21))/Assumptions!$E$6 -> 1.5763635
A10: 2250 | B10: =(Assumptions!$B$6*$A10*12*(1-B$4)*(1-Assumptions!$B$21))/Assumptions!$E$6 -> 1.7173327 | C10: =(Assumptions!$B$6*$A10*12*(1-C$4)*(1-Assumptions!$B$21))/Assumptions!$E$6 -> 1.6998089 | D10: =(Assumptions!$B$6*$A10*12*(1-D$4)*(1-Assumptions!$B$21))/Assumptions!$E$6 -> 1.6822851 | E10: =(Assumptions!$B$6*$A10*12*(1-E$4)*(1-Assumptions!$B$21))/Assumptions!$E$6 -> 1.6647613 | F10: =(Assumptions!$B$6*$A10*12*(1-F$4)*(1-Assumptions!$B$21))/Assumptions!$E$6 -> 1.6472375 | G10: =(Assumptions!$B$6*$A10*12*(1-G$4)*(1-Assumptions!$B$21))/Assumptions!$E$6 -> 1.6297137 | H10: =(Assumptions!$B$6*$A10*12*(1-H$4)*(1-Assumptions!$B$21))/Assumptions!$E$6 -> 1.6121899
A11: 2300 | B11: =(Assumptions!$B$6*$A11*12*(1-B$4)*(1-Assumptions!$B$21))/Assumptions!$E$6 -> 1.7554957 | C11: =(Assumptions!$B$6*$A11*12*(1-C$4)*(1-Assumptions!$B$21))/Assumptions!$E$6 -> 1.7375825 | D11: =(Assumptions!$B$6*$A11*12*(1-D$4)*(1-Assumptions!$B$21))/Assumptions!$E$6 -> 1.7196692 | E11: =(Assumptions!$B$6*$A11*12*(1-E$4)*(1-Assumptions!$B$21))/Assumptions!$E$6 -> 1.701756 | F11: =(Assumptions!$B$6*$A11*12*(1-F$4)*(1-Assumptions!$B$21))/Assumptions!$E$6 -> 1.6838428 | G11: =(Assumptions!$B$6*$A11*12*(1-G$4)*(1-Assumptions!$B$21))/Assumptions!$E$6 -> 1.6659296 | H11: =(Assumptions!$B$6*$A11*12*(1-H$4)*(1-Assumptions!$B$21))/Assumptions!$E$6 -> 1.6480164
A14: 20-Yr Landowner Cumulative Income — Rent (rows) × Rent Growth (cols)
A16: Cum Income | B16: 0.01 | C16: 0.015 | D16: 0.02 | E16: 0.025 | F16: 0.03 | G16: 0.035 | H16: 0.04
A17: 2000 | B17: =Assumptions!$B$22*(Assumptions!$B$6*$A17*12*(1-Assumptions!$B$20)*(1-Assumptions!$B$21)*((1+B$16)^Assumptions!$B$35-1)/B$16-Assumptions!$E$6*Assumptions!$B$35) -> 2268407.8 | C17: =Assumptions!$B$22*(Assumptions!$B$6*$A17*12*(1-Assumptions!$B$20)*(1-Assumptions!$B$21)*((1+C$16)^Assumptions!$B$35-1)/C$16-Assumptions!$E$6*Assumptions!$B$35) -> 2563087.8 | D17: =Assumptions!$B$22*(Assumptions!$B$6*$A17*12*(1-Assumptions!$B$20)*(1-Assumptions!$B$21)*((1+D$16)^Assumptions!$B$35-1)/D$16-Assumptions!$E$6*Assumptions!$B$35) -> 2876184.7 | E17: =Assumptions!$B$22*(Assumptions!$B$6*$A17*12*(1-Assumptions!$B$20)*(1-Assumptions!$B$21)*((1+E$16)^Assumptions!$B$35-1)/E$16-Assumptions!$E$6*Assumptions!$B$35) -> 3208911.2 | F17: =Assumptions!$B$22*(Assumptions!$B$6*$A17*12*(1-Assumptions!$B$20)*(1-Assumptions!$B$21)*((1+F$16)^Assumptions!$B$35-1)/F$16-Assumptions!$E$6*Assumptions!$B$35) -> 3562559.4 | G17: =Assumptions!$B$22*(Assumptions!$B$6*$A17*12*(1-Assumptions!$B$20)*(1-Assumptions!$B$21)*((1+G$16)^Assumptions!$B$35-1)/G$16-Assumptions!$E$6*Assumptions!$B$35) -> 3938506.2 | H17: =Assumptions!$B$22*(Assumptions!$B$6*$A17*12*(1-Assumptions!$B$20)*(1-Assumptions!$B$21)*((1+H$16)^Assumptions!$B$35-1)/H$16-Assumptions!$E$6*Assumptions!$B$35) -> 4338218.6
A18: 2050 | B18: =Assumptions!$B$22*(Assumptions!$B$6*$A18*12*(1-Assumptions!$B$20)*(1-Assumptions!$B$21)*((1+B$16)^Assumptions!$B$35-1)/B$16-Assumptions!$E$6*Assumptions!$B$35) -> 2415252.6 | C18: =Assumptions!$B$22*(Assumptions!$B$6*$A18*12*(1-Assumptions!$B$20)*(1-Assumptions!$B$21)*((1+C$16)^Assumptions!$B$35-1)/C$16-Assumptions!$E$6*Assumptions!$B$35) -> 2717299.5 | D18: =Assumptions!$B$22*(Assumptions!$B$6*$A18*12*(1-Assumptions!$B$20)*(1-Assumptions!$B$21)*((1+D$16)^Assumptions!$B$35-1)/D$16-Assumptions!$E$6*Assumptions!$B$35) -> 3038223.8 | E18: =Assumptions!$B$22*(Assumptions!$B$6*$A18*12*(1-Assumptions!$B$20)*(1-Assumptions!$B$21)*((1+E$16)^Assumptions!$B$35-1)/E$16-Assumptions!$E$6*Assumptions!$B$35) -> 3379268.5 | F18: =Assumptions!$B$22*(Assumptions!$B$6*$A18*12*(1-Assumptions!$B$20)*(1-Assumptions!$B$21)*((1+F$16)^Assumptions!$B$35-1)/F$16-Assumptions!$E$6*Assumptions!$B$35) -> 3741757.9 | G18: =Assumptions!$B$22*(Assumptions!$B$6*$A18*12*(1-Assumptions!$B$20)*(1-Assumptions!$B$21)*((1+G$16)^Assumptions!$B$35-1)/G$16-Assumptions!$E$6*Assumptions!$B$35) -> 4127103.4 | H18: =Assumptions!$B$22*(Assumptions!$B$6*$A18*12*(1-Assumptions!$B$20)*(1-Assumptions!$B$21)*((1+H$16)^Assumptions!$B$35-1)/H$16-Assumptions!$E$6*Assumptions!$B$35) -> 4536808.6
A19: 2100 | B19: =Assumptions!$B$22*(Assumptions!$B$6*$A19*12*(1-Assumptions!$B$20)*(1-Assumptions!$B$21)*((1+B$16)^Assumptions!$B$35-1)/B$16-Assumptions!$E$6*Assumptions!$B$35) -> 2562097.3 | C19: =Assumptions!$B$22*(Assumptions!$B$6*$A19*12*(1-Assumptions!$B$20)*(1-Assumptions!$B$21)*((1+C$16)^Assumptions!$B$35-1)/C$16-Assumptions!$E$6*Assumptions!$B$35) -> 2871511.2 | D19: =Assumptions!$B$22*(Assumptions!$B$6*$A19*12*(1-Assumptions!$B$20)*(1-Assumptions!$B$21)*((1+D$16)^Assumptions!$B$35-1)/D$16-Assumptions!$E$6*Assumptions!$B$35) -> 3200263 | E19: =Assumptions!$B$22*(Assumptions!$B$6*$A19*12*(1-Assumptions!$B$20)*(1-Assumptions!$B$21)*((1+E$16)^Assumptions!$B$35-1)/E$16-Assumptions!$E$6*Assumptions!$B$35) -> 3549625.8 | F19: =Assumptions!$B$22*(Assumptions!$B$6*$A19*12*(1-Assumptions!$B$20)*(1-Assumptions!$B$21)*((1+F$16)^Assumptions!$B$35-1)/F$16-Assumptions!$E$6*Assumptions!$B$35) -> 3920956.5 | G19: =Assumptions!$B$22*(Assumptions!$B$6*$A19*12*(1-Assumptions!$B$20)*(1-Assumptions!$B$21)*((1+G$16)^Assumptions!$B$35-1)/G$16-Assumptions!$E$6*Assumptions!$B$35) -> 4315700.6 | H19: =Assumptions!$B$22*(Assumptions!$B$6*$A19*12*(1-Assumptions!$B$20)*(1-Assumptions!$B$21)*((1+H$16)^Assumptions!$B$35-1)/H$16-Assumptions!$E$6*Assumptions!$B$35) -> 4735398.6
A20: 2150 | B20: =Assumptions!$B$22*(Assumptions!$B$6*$A20*12*(1-Assumptions!$B$20)*(1-Assumptions!$B$21)*((1+B$16)^Assumptions!$B$35-1)/B$16-Assumptions!$E$6*Assumptions!$B$35) -> 2708942 | C20: =Assumptions!$B$22*(Assumptions!$B$6*$A20*12*(1-Assumptions!$B$20)*(1-Assumptions!$B$21)*((1+C$16)^Assumptions!$B$35-1)/C$16-Assumptions!$E$6*Assumptions!$B$35) -> 3025723 | D20: =Assumptions!$B$22*(Assumptions!$B$6*$A20*12*(1-Assumptions!$B$20)*(1-Assumptions!$B$21)*((1+D$16)^Assumptions!$B$35-1)/D$16-Assumptions!$E$6*Assumptions!$B$35) -> 3362302.2 | E20: =Assumptions!$B$22*(Assumptions!$B$6*$A20*12*(1-Assumptions!$B$20)*(1-Assumptions!$B$21)*((1+E$16)^Assumptions!$B$35-1)/E$16-Assumptions!$E$6*Assumptions!$B$35) -> 3719983.2 | F20: =Assumptions!$B$22*(Assumptions!$B$6*$A20*12*(1-Assumptions!$B$20)*(1-Assumptions!$B$21)*((1+F$16)^Assumptions!$B$35-1)/F$16-Assumptions!$E$6*Assumptions!$B$35) -> 4100155 | G20: =Assumptions!$B$22*(Assumptions!$B$6*$A20*12*(1-Assumptions!$B$20)*(1-Assumptions!$B$21)*((1+G$16)^Assumptions!$B$35-1)/G$16-Assumptions!$E$6*Assumptions!$B$35) -> 4504297.8 | H20: =Assumptions!$B$22*(Assumptions!$B$6*$A20*12*(1-Assumptions!$B$20)*(1-Assumptions!$B$21)*((1+H$16)^Assumptions!$B$35-1)/H$16-Assumptions!$E$6*Assumptions!$B$35) -> 4933988.6
A21: 2200 | B21: =Assumptions!$B$22*(Assumptions!$B$6*$A21*12*(1-Assumptions!$B$20)*(1-Assumptions!$B$21)*((1+B$16)^Assumptions!$B$35-1)/B$16-Assumptions!$E$6*Assumptions!$B$35) -> 2855786.8 | C21: =Assumptions!$B$22*(Assumptions!$B$6*$A21*12*(1-Assumptions!$B$20)*(1-Assumptions!$B$21)*((1+C$16)^Assumptions!$B$35-1)/C$16-Assumptions!$E$6*Assumptions!$B$35) -> 3179934.7 | D21: =Assumptions!$B$22*(Assumptions!$B$6*$A21*12*(1-Assumptions!$B$20)*(1-Assumptions!$B$21)*((1+D$16)^Assumptions!$B$35-1)/D$16-Assumptions!$E$6*Assumptions!$B$35) -> 3524341.3 | E21: =Assumptions!$B$22*(Assumptions!$B$6*$A21*12*(1-Assumptions!$B$20)*(1-Assumptions!$B$21)*((1+E$16)^Assumptions!$B$35-1)/E$16-Assumptions!$E$6*Assumptions!$B$35) -> 3890340.5 | F21: =Assumptions!$B$22*(Assumptions!$B$6*$A21*12*(1-Assumptions!$B$20)*(1-Assumptions!$B$21)*((1+F$16)^Assumptions!$B$35-1)/F$16-Assumptions!$E$6*Assumptions!$B$35) -> 4279353.5 | G21: =Assumptions!$B$22*(Assumptions!$B$6*$A21*12*(1-Assumptions!$B$20)*(1-Assumptions!$B$21)*((1+G$16)^Assumptions!$B$35-1)/G$16-Assumptions!$E$6*Assumptions!$B$35) -> 4692895 | H21: =Assumptions!$B$22*(Assumptions!$B$6*$A21*12*(1-Assumptions!$B$20)*(1-Assumptions!$B$21)*((1+H$16)^Assumptions!$B$35-1)/H$16-Assumptions!$E$6*Assumptions!$B$35) -> 5132578.6
A22: 2250 | B22: =Assumptions!$B$22*(Assumptions!$B$6*$A22*12*(1-Assumptions!$B$20)*(1-Assumptions!$B$21)*((1+B$16)^Assumptions!$B$35-1)/B$16-Assumptions!$E$6*Assumptions!$B$35) -> 3002631.5 | C22: =Assumptions!$B$22*(Assumptions!$B$6*$A22*12*(1-Assumptions!$B$20)*(1-Assumptions!$B$21)*((1+C$16)^Assumptions!$B$35-1)/C$16-Assumptions!$E$6*Assumptions!$B$35) -> 3334146.4 | D22: =Assumptions!$B$22*(Assumptions!$B$6*$A22*12*(1-Assumptions!$B$20)*(1-Assumptions!$B$21)*((1+D$16)^Assumptions!$B$35-1)/D$16-Assumptions!$E$6*Assumptions!$B$35) -> 3686380.5 | E22: =Assumptions!$B$22*(Assumptions!$B$6*$A22*12*(1-Assumptions!$B$20)*(1-Assumptions!$B$21)*((1+E$16)^Assumptions!$B$35-1)/E$16-Assumptions!$E$6*Assumptions!$B$35) -> 4060697.8 | F22: =Assumptions!$B$22*(Assumptions!$B$6*$A22*12*(1-Assumptions!$B$20)*(1-Assumptions!$B$21)*((1+F$16)^Assumptions!$B$35-1)/F$16-Assumptions!$E$6*Assumptions!$B$35) -> 4458552.1 | G22: =Assumptions!$B$22*(Assumptions!$B$6*$A22*12*(1-Assumptions!$B$20)*(1-Assumptions!$B$21)*((1+G$16)^Assumptions!$B$35-1)/G$16-Assumptions!$E$6*Assumptions!$B$35) -> 4881492.2 | H22: =Assumptions!$B$22*(Assumptions!$B$6*$A22*12*(1-Assumptions!$B$20)*(1-Assumptions!$B$21)*((1+H$16)^Assumptions!$B$35-1)/H$16-Assumptions!$E$6*Assumptions!$B$35) -> 5331168.6
A23: 2300 | B23: =Assumptions!$B$22*(Assumptions!$B$6*$A23*12*(1-Assumptions!$B$20)*(1-Assumptions!$B$21)*((1+B$16)^Assumptions!$B$35-1)/B$16-Assumptions!$E$6*Assumptions!$B$35) -> 3149476.3 | C23: =Assumptions!$B$22*(Assumptions!$B$6*$A23*12*(1-Assumptions!$B$20)*(1-Assumptions!$B$21)*((1+C$16)^Assumptions!$B$35-1)/C$16-Assumptions!$E$6*Assumptions!$B$35) -> 3488358.2 | D23: =Assumptions!$B$22*(Assumptions!$B$6*$A23*12*(1-Assumptions!$B$20)*(1-Assumptions!$B$21)*((1+D$16)^Assumptions!$B$35-1)/D$16-Assumptions!$E$6*Assumptions!$B$35) -> 3848419.6 | E23: =Assumptions!$B$22*(Assumptions!$B$6*$A23*12*(1-Assumptions!$B$20)*(1-Assumptions!$B$21)*((1+E$16)^Assumptions!$B$35-1)/E$16-Assumptions!$E$6*Assumptions!$B$35) -> 4231055.1 | F23: =Assumptions!$B$22*(Assumptions!$B$6*$A23*12*(1-Assumptions!$B$20)*(1-Assumptions!$B$21)*((1+F$16)^Assumptions!$B$35-1)/F$16-Assumptions!$E$6*Assumptions!$B$35) -> 4637750.6 | G23: =Assumptions!$B$22*(Assumptions!$B$6*$A23*12*(1-Assumptions!$B$20)*(1-Assumptions!$B$21)*((1+G$16)^Assumptions!$B$35-1)/G$16-Assumptions!$E$6*Assumptions!$B$35) -> 5070089.4 | H23: =Assumptions!$B$22*(Assumptions!$B$6*$A23*12*(1-Assumptions!$B$20)*(1-Assumptions!$B$21)*((1+H$16)^Assumptions!$B$35-1)/H$16-Assumptions!$E$6*Assumptions!$B$35) -> 5529758.6

Sheet Landowner Waterfall
A1: Landowner Total Return — 20-Year Waterfall
A3: Component | B3: Timing | C3: Period Income ($) | D3: Cumulative ($) | E3: Notes
A4: Day 1 Cash Payment | B4: Day 1 | C4: =Assumptions!B13 -> 1400000 | D4: =C4 -> 1400000 | E4: First construction draw
A5: Year 1 Net Cash Flow Distribution | B5: Year 1 | C5: ='Pro Forma'!B12 -> 106497.92 | D5: =D4+C5 -> 1506497.9 | E5: 60% of NCF after debt service
A6: Years 2-5 Income | B6: Year 5 | C6: =SUM('Pro Forma'!C12:F12) -> 484503.65 | D6: =D5+C6 -> 1991001.6 | E6: Cumulative through Year 5
A7: Years 6-10 Income | B7: Year 10 | C7: =SUM('Pro Forma'!G12:K12) -> 746326.24 | D7: =D6+C7 -> 2737327.8 | E7: Cumulative through Year 10
A8: Years 11-15 Income | B8: Year 15 | C8: =SUM('Pro Forma'!L12:P12) -> 917817.23 | D8: =D7+C8 -> 3655145 | E8: Cumulative through Year 15
A9: Years 16-20 Income | B9: Year 20 | C9: =SUM('Pro Forma'!Q12:U12) -> 1107157.1 | D9: =D8+C9 -> 4762302.2 | E9: Cumulative through Year 20
A10: Year 20 Equity Return | B10: Year 20 | C10: =Dashboard!B11 -> 600000 | D10: =D9+C10 -> 5362302.2 | E10: Original $600K equity returned
A11: TOTAL TO LANDOWNER | D11: =D10 -> 5362302.2 | E11: Day 1 + 20-yr income + Year 20 equity
A13: COMPARISON: BCH vs Conventional Sale
A14: Cash sale today (low) | B14: 1200000
A15: Cash sale today (high) | B15: 1600000
A16: Sale + VTB structure (best case) | B16: 2000000
A17: → VTB note carried by seller; subject to buyer payment performance
A18: BCH route — Day 1 cash (no VTB risk) | B18: =Assumptions!B13 -> 1400000
A19: BCH route — 20-yr cumulative income | B19: ='Pro Forma'!V12 -> 3362302.2
A20: BCH route — Year 20 equity return | B20: =Dashboard!B11 -> 600000
A21: BCH route total | B21: =B18+B19+B20 -> 5362302.2
A22: BCH advantage vs $1.4M cash sale midpoint | B22: =B21-(B14+B15)/2 -> 3962302.2
A24: RETURN METRICS
A25: Land Contributed (BCH valuation) | B25: =-Assumptions!B12 -> -2000000
A26: Day 1 Cash + Year 1 NCF | B26: =Assumptions!B13+'Pro Forma'!B12 -> 1506497.9
A27: Years 2-20 NCF + Year 20 equity (combined Y20)
A28: Landowner IRR | B28: =IRR(B30:V30) -> 0.22035623
A29: Equity Multiple (Total Inflows / Land In) | B29: =(Assumptions!B13+'Pro Forma'!V12+Dashboard!B11)/Assumptions!B12 -> 2.6811511
A30: Cash Flow Series (for IRR) | B30: =-Assumptions!B12+Assumptions!B13 -> -600000 | C30: ='Pro Forma'!B12 -> 106497.92 | D30: ='Pro Forma'!C12 -> 112233.26 | E30: ='Pro Forma'!D12 -> 118083.3 | F30: ='Pro Forma'!E12 -> 124050.35 | G30: ='Pro Forma'!F12 -> 130136.74 | H30: ='Pro Forma'!G12 -> 136344.86 | I30: ='Pro Forma'!H12 -> 142677.13 | J30: ='Pro Forma'!I12 -> 149136.06 | ... U30: ='Pro Forma'!T12 -> 229304.81 | V30: ='Pro Forma'!U12+Dashboard!B11 -> 837496.29
A31: Year | B31: 0 | C31: 1

Sheet 24-Unit Alternative
A1: 24-Unit Alternative Configuration
A2: Smaller envelope · Same site · Same capital stack proportions
A4: PROJECT FUNDAMENTALS
A5: Total Units | B5: 24
A6: Cost per Unit | B6: =Assumptions!B7 -> 411343
A7: Total Project Cost | B7: =B5*B6 -> 9872232
A8: Avg Monthly Rent | B8: 2200
A9: Year 1 NOI | B9: =B5*B8*12*(1-Assumptions!B20)*(1-Assumptions!B21) -> 391248
A10: Year 1 Annual Debt Service | B10: =-PMT(Assumptions!B32/12,Assumptions!B33*12,B7*Assumptions!B27)*12 -> 240358.78
A11: Year 1 Net Cash Flow | B11: =B9-B10 -> 150889.22
A12: Year 1 Landowner Distribution (60%) | B12: =B11*Assumptions!B22 -> 90533.533
A13: DSCR (Year 1) | B13: =B9/B10 -> 1.6277666
A14: LTV | B14: =Assumptions!B27 -> 0.5
A15: 20-Yr Landowner Cumulative Income | B15: =Assumptions!B22*(B5*B8*12*(1-Assumptions!B20)*(1-Assumptions!B21)*((1+Assumptions!B19)^Assumptions!B35-1)/Assumptions!B19-B10*Assumptions!B35) -> 2819473.1
A16: Day 1 Cash to Landowner | B16: =Assumptions!B13 -> 1400000
A17: Landowner Retained Equity | B17: =B7*Assumptions!B29 -> 479790.48
A18: Year 20 Equity Return | B18: =Assumptions!B15 -> 600000
A19: TOTAL LANDOWNER RETURN | B19: =B16+B15+B18 -> 4819473.1
A20: Year 20 Mortgage Paydown (NFP) | B20: =-CUMPRINC(Assumptions!B32/12,Assumptions!B33*12,B7*Assumptions!B27,1,Assumptions!B35*12,0) -> 888620.73
